mong/__init__.py
mong/create_dict.py
mong/moby_dict.json
mong/name_generator.py
mong/py.typed
mong-0.0.3.dist-info/LICENSE
mong-0.0.3.dist-info/METADATA
mong-0.0.3.dist-info/WHEEL
mong-0.0.3.dist-info/top_level.txt
mong-0.0.3.dist-info/RECORD
